{
	"id": "WdEtdpGh2oynJVu",
	"json": "{\"id\":\"WdEtdpGh2oynJVu\",\"url\":\"https://weworkremotely.com//remote-jobs/c4media-inc-mobile-developer\",\"loadedUrl\":\"https://weworkremotely.com//remote-jobs/c4media-inc-mobile-developer\",\"uniqueKey\":\"https://weworkremotely.com//remote-jobs/c4media-inc-mobile-developer\",\"method\":\"GET\",\"noRetry\":false,\"retryCount\":0,\"errorMessages\":[],\"headers\":{},\"userData\":{\"label\":\"DETAIL\",\"__crawlee\":{\"crawlDepth\":1,\"enqueueStrategy\":\"same-hostname\",\"state\":4}},\"handledAt\":\"2026-04-20T18:11:20.656Z\"}",
	"method": "GET",
	"orderNo": null,
	"retryCount": 0,
	"uniqueKey": "https://weworkremotely.com//remote-jobs/c4media-inc-mobile-developer",
	"url": "https://weworkremotely.com//remote-jobs/c4media-inc-mobile-developer"
}